keyauth/__init__.py
keyauth/client.py
keyauth/encryption.py
keyauth/errors.py
keyauth/types.py
keyauth/utils.py
keyauthy-0.2.dist-info/LICENSE
keyauthy-0.2.dist-info/METADATA
keyauthy-0.2.dist-info/WHEEL
keyauthy-0.2.dist-info/top_level.txt
keyauthy-0.2.dist-info/RECORD
