Metadata-Version: 2.1
Name: keyauthy
Version: 0.2
Summary: Api Wrapper for KeyAuth.com
Home-page: UNKNOWN
Author: Mohanad Hosny
License: UNKNOWN
Keywords: wrapper,apiwrapper,keyauth,auth,authsystem
Platform: UNKNOWN
Classifier: Intended Audience :: Developers
Classifier: Programming Language :: Python :: 3
Classifier: Operating System :: Unix
Classifier: Operating System :: MacOS :: MacOS X
Classifier: Operating System :: Microsoft :: Windows
License-File: LICENSE
Requires-Dist: requests
Requires-Dist: pycryptodome
